chuckquotes/__init__.py
chuck_quotes-0.2.1.dist-info/WHEEL
chuck_quotes-0.2.1.dist-info/METADATA
chuck_quotes-0.2.1.dist-info/RECORD
