Metadata-Version: 2.1
Name: chuck-quotes
Version: 0.2.1
Summary: 
Author: Juanjo Salvador
Author-email: juanjosalvador@netc.eu
Requires-Python: >=3.10,<4.0
Classifier: Programming Language :: Python :: 3
Classifier: Programming Language :: Python :: 3.10
Classifier: Programming Language :: Python :: 3.11
Requires-Dist: requests (>=2.28.1,<3.0.0)
